verifit/__init__.py
verifit/cache.py
verifit/date_tools.py
verifit/endpoint_tools.py
verifit/json_web_token.py
verifit/login.py
verifit-5.0.2.dist-info/LICENSE
verifit-5.0.2.dist-info/METADATA
verifit-5.0.2.dist-info/WHEEL
verifit-5.0.2.dist-info/top_level.txt
verifit-5.0.2.dist-info/RECORD
