Metadata-Version: 2.1
Name: verifit
Version: 5.0.2
Summary: Verify It: Small automatic testing helper tools
Author-email: Sorel Mitra <sorelmitra@yahoo.com>
License: MIT License
Project-URL: Homepage, https://github.com/sorelmitra/verifit
Keywords: automatic testing tools,acceptance testing tools
Classifier: License :: OSI Approved :: MIT License
Classifier: Programming Language :: Python
Classifier: Programming Language :: Python :: 3
Requires-Python: >=3.9
License-File: LICENSE
Requires-Dist: PyJWT
Requires-Dist: pytest
Provides-Extra: dev
